README.md
setup.cfg
setup.py
AquesTalk_python.egg-info/PKG-INFO
AquesTalk_python.egg-info/SOURCES.txt
AquesTalk_python.egg-info/dependency_links.txt
AquesTalk_python.egg-info/top_level.txt
aquestalk/__init__.py
aquestalk/aquestalk.py
aquestalk/dvd/AqLicense.txt
aquestalk/dvd/AquesTalk.dll
aquestalk/f1/AqLicence.txt
aquestalk/f1/AquesTalk.dll
aquestalk/f2/AqLicence.txt
aquestalk/f2/AquesTalk.dll
aquestalk/imd1/AqLicense.txt
aquestalk/imd1/AquesTalk.dll
aquestalk/jgr/AqLicense.txt
aquestalk/jgr/AquesTalk.dll
aquestalk/m1/AqLicence.txt
aquestalk/m1/AquesTalk.dll
aquestalk/m2/AqLicence.txt
aquestalk/m2/AquesTalk.dll
aquestalk/r1/AqLicence.txt
aquestalk/r1/AquesTalk.dll