Metadata-Version: 2.1
Name: AquesTalk-python
Version: 1.1
Summary: Python Wrapper for AquesTalk (Old License)
Home-page: https://github.com/Na-x4/AquesTalk-python
Author: Na-x4
License: GNU General Public License v3
Platform: UNKNOWN
Classifier: Programming Language :: Python :: 3
Classifier: License :: OSI Approved :: GNU General Public License v3 (GPLv3)
Classifier: Operating System :: Microsoft :: Windows
Classifier: Natural Language :: Japanese
Classifier: Topic :: Multimedia :: Sound/Audio :: Speech
